lmlogits-0.1.1.dist-info/METADATA
lmlogits-0.1.1.dist-info/WHEEL
lmlogits/__init__.py
lmlogits/lmlogits.pypy38-pp73-aarch64-linux-gnu.so
lmlogits-0.1.1.dist-info/RECORD
